[{"name":"render_partial.action_view","payload":{"identifier":"/Users/bonnie/Desktop/code/reumanager/app/views/applicants/shared/_links.erb"},"time":"2016-01-13T14:57:32.107-08:00","transaction_id":"db06dce168c2b63406c4","end":"2016-01-13T14:57:32.108-08:00","children":[],"duration":0.858},{"name":"render_template.action_view","payload":{"identifier":"/Users/bonnie/Desktop/code/reumanager/app/views/applicants/sessions/new.html.erb","layout":"layouts/application"},"time":"2016-01-13T14:57:32.105-08:00","transaction_id":"db06dce168c2b63406c4","end":"2016-01-13T14:57:32.109-08:00","children":[],"duration":3.575},{"name":"sql.active_record","payload":{"sql":"SELECT  `settings`.* FROM `settings`  WHERE `settings`.`name` = 'app_title' LIMIT 1","name":"Setting Load","connection_id":2159028660,"statement_name":null,"binds":[]},"time":"2016-01-13T14:57:32.109-08:00","transaction_id":"696db1163a5f0aa4bb32","end":"2016-01-13T14:57:32.110-08:00","children":[],"duration":0.9039999999999999},{"name":"sql.active_record","payload":{"sql":"SELECT  `settings`.* FROM `settings`  WHERE `settings`.`name` = 'university' LIMIT 1","name":"Setting Load","connection_id":2159028660,"statement_name":null,"binds":[]},"time":"2016-01-13T14:57:32.115-08:00","transaction_id":"696db1163a5f0aa4bb32","end":"2016-01-13T14:57:32.117-08:00","children":[],"duration":1.206},{"name":"sql.active_record","payload":{"sql":"SELECT  `settings`.* FROM `settings`  WHERE `settings`.`name` = 'university_url' LIMIT 1","name":"Setting Load","connection_id":2159028660,"statement_name":null,"binds":[]},"time":"2016-01-13T14:57:32.117-08:00","transaction_id":"696db1163a5f0aa4bb32","end":"2016-01-13T14:57:32.118-08:00","children":[],"duration":0.821},{"name":"sql.active_record","payload":{"sql":"SELECT  `settings`.* FROM `settings`  WHERE `settings`.`name` = 'department' LIMIT 1","name":"Setting Load","connection_id":2159028660,"statement_name":null,"binds":[]},"time":"2016-01-13T14:57:32.119-08:00","transaction_id":"696db1163a5f0aa4bb32","end":"2016-01-13T14:57:32.120-08:00","children":[],"duration":0.713},{"name":"sql.active_record","payload":{"sql":"SELECT  `settings`.* FROM `settings`  WHERE `settings`.`name` = 'department_url' LIMIT 1","name":"Setting Load","connection_id":2159028660,"statement_name":null,"binds":[]},"time":"2016-01-13T14:57:32.121-08:00","transaction_id":"696db1163a5f0aa4bb32","end":"2016-01-13T14:57:32.122-08:00","children":[],"duration":0.976},{"name":"sql.active_record","payload":{"sql":"SELECT  `settings`.* FROM `settings`  WHERE `settings`.`name` = 'app_title' LIMIT 1","binds":[],"name":"CACHE","connection_id":2159028660},"time":"2016-01-13T14:57:32.123-08:00","transaction_id":"db06dce168c2b63406c4","end":"2016-01-13T14:57:32.124-08:00","children":[],"duration":0.637},{"name":"sql.active_record","payload":{"sql":"SELECT  `settings`.* FROM `settings`  WHERE `settings`.`name` = 'program_start_date' LIMIT 1","name":"Setting Load","connection_id":2159028660,"statement_name":null,"binds":[]},"time":"2016-01-13T14:57:32.124-08:00","transaction_id":"696db1163a5f0aa4bb32","end":"2016-01-13T14:57:32.125-08:00","children":[],"duration":0.972},{"name":"sql.active_record","payload":{"sql":"SELECT  `settings`.* FROM `settings`  WHERE `settings`.`name` = 'program_end_date' LIMIT 1","name":"Setting Load","connection_id":2159028660,"statement_name":null,"binds":[]},"time":"2016-01-13T14:57:32.126-08:00","transaction_id":"696db1163a5f0aa4bb32","end":"2016-01-13T14:57:32.127-08:00","children":[],"duration":0.712},{"name":"sql.active_record","payload":{"sql":"SELECT  `settings`.* FROM `settings`  WHERE `settings`.`name` = 'program_url' LIMIT 1","name":"Setting Load","connection_id":2159028660,"statement_name":null,"binds":[]},"time":"2016-01-13T14:57:32.128-08:00","transaction_id":"696db1163a5f0aa4bb32","end":"2016-01-13T14:57:32.129-08:00","children":[],"duration":0.752},{"name":"render_partial.action_view","payload":{"identifier":"/Users/bonnie/Desktop/code/reumanager/app/views/layouts/_header.html.haml"},"time":"2016-01-13T14:57:32.115-08:00","transaction_id":"db06dce168c2b63406c4","end":"2016-01-13T14:57:32.129-08:00","children":[],"duration":14.652999999999999},{"name":"render_partial.action_view","payload":{"identifier":"/Users/bonnie/Desktop/code/reumanager/app/views/layouts/_navbar.html.haml"},"time":"2016-01-13T14:57:32.130-08:00","transaction_id":"db06dce168c2b63406c4","end":"2016-01-13T14:57:32.132-08:00","children":[],"duration":1.556},{"name":"sql.active_record","payload":{"sql":"SELECT  `settings`.* FROM `settings`  WHERE `settings`.`name` = 'department' LIMIT 1","binds":[],"name":"CACHE","connection_id":2159028660},"time":"2016-01-13T14:57:32.133-08:00","transaction_id":"db06dce168c2b63406c4","end":"2016-01-13T14:57:32.133-08:00","children":[],"duration":0.416},{"name":"sql.active_record","payload":{"sql":"SELECT  `settings`.* FROM `settings`  WHERE `settings`.`name` = 'department_url' LIMIT 1","binds":[],"name":"CACHE","connection_id":2159028660},"time":"2016-01-13T14:57:32.134-08:00","transaction_id":"db06dce168c2b63406c4","end":"2016-01-13T14:57:32.134-08:00","children":[],"duration":0.422},{"name":"sql.active_record","payload":{"sql":"SELECT  `settings`.* FROM `settings`  WHERE `settings`.`name` = 'department_postal_address' LIMIT 1","name":"Setting Load","connection_id":2159028660,"statement_name":null,"binds":[]},"time":"2016-01-13T14:57:32.135-08:00","transaction_id":"696db1163a5f0aa4bb32","end":"2016-01-13T14:57:32.136-08:00","children":[],"duration":0.757},{"name":"sql.active_record","payload":{"sql":"SELECT  `settings`.* FROM `settings`  WHERE `settings`.`name` = 'mail_from' LIMIT 1","name":"Setting Load","connection_id":2159028660,"statement_name":null,"binds":[]},"time":"2016-01-13T14:57:32.137-08:00","transaction_id":"696db1163a5f0aa4bb32","end":"2016-01-13T14:57:32.137-08:00","children":[],"duration":0.737},{"name":"sql.active_record","payload":{"sql":"SELECT  `settings`.* FROM `settings`  WHERE `settings`.`name` = 'funding_acknowlegement' LIMIT 1","name":"Setting Load","connection_id":2159028660,"statement_name":null,"binds":[]},"time":"2016-01-13T14:57:32.138-08:00","transaction_id":"696db1163a5f0aa4bb32","end":"2016-01-13T14:57:32.139-08:00","children":[],"duration":0.82},{"name":"render_partial.action_view","payload":{"identifier":"/Users/bonnie/Desktop/code/reumanager/app/views/layouts/_footer_text.html.erb"},"time":"2016-01-13T14:57:32.132-08:00","transaction_id":"db06dce168c2b63406c4","end":"2016-01-13T14:57:32.140-08:00","children":[],"duration":7.679},{"name":"process_action.action_controller","payload":{"controller":"Applicants::SessionsController","action":"new","params":{"action":"new","controller":"applicants/sessions"},"format":"html","method":"GET","path":"/applicants/sign_in","status":200,"view_runtime":37.632000000000005,"db_runtime":4.071999999999999},"time":"2016-01-13T14:57:32.097-08:00","transaction_id":"db06dce168c2b63406c4","end":"2016-01-13T14:57:32.141-08:00","children":[],"duration":43.922000000000004}]